astar/__init__.py
astar/demo.py
astar/search.py
test/__init__.py
test/test_astar.py
python_astar-0.1.0.dist-info/LICENSE
python_astar-0.1.0.dist-info/METADATA
python_astar-0.1.0.dist-info/WHEEL
python_astar-0.1.0.dist-info/top_level.txt
python_astar-0.1.0.dist-info/RECORD
