Metadata-Version: 2.1
Name: python-astar
Version: 0.1.0
Summary: A simplistic A* path search tool
Home-page: 
Author: Gustavo Selbach Teixeira
Author-email: gsteixei@gmail.com
License: GNU License
Classifier: Development Status :: 5 - Production/Stable
Classifier: Intended Audience :: Education
Classifier: Intended Audience :: Science/Research
Classifier: Topic :: Scientific/Engineering :: Artificial Intelligence
Classifier: Topic :: Utilities
License-File: LICENSE
